odoo/addons/sale_blanket_order_contact_person/LICENSE
odoo/addons/sale_blanket_order_contact_person/README.rst
odoo/addons/sale_blanket_order_contact_person/__init__.py
odoo/addons/sale_blanket_order_contact_person/__manifest__.py
odoo/addons/sale_blanket_order_contact_person/i18n/de.po
odoo/addons/sale_blanket_order_contact_person/images/screen.png
odoo/addons/sale_blanket_order_contact_person/models/__init__.py
odoo/addons/sale_blanket_order_contact_person/models/blanket_order.py
odoo/addons/sale_blanket_order_contact_person/models/sale_order.py
odoo/addons/sale_blanket_order_contact_person/static/description/icon.png
odoo/addons/sale_blanket_order_contact_person/static/description/index.html
odoo/addons/sale_blanket_order_contact_person/tests/TEST_INSTRUCTIONS.rst
odoo/addons/sale_blanket_order_contact_person/views/sale_blanket_order.xml
odoo_addon_sale_blanket_order_contact_person-16.0.1.0.1.dist-info/METADATA
odoo_addon_sale_blanket_order_contact_person-16.0.1.0.1.dist-info/WHEEL
odoo_addon_sale_blanket_order_contact_person-16.0.1.0.1.dist-info/top_level.txt
odoo_addon_sale_blanket_order_contact_person-16.0.1.0.1.dist-info/RECORD
